Workbook
Name Slicer_Category: #N/A
Name Slicer_Region: #N/A
Name Slicer_Salesperson: #N/A

Sheet Pivot
A3: Row Labels | B3: Sum of Net_Sales | D3: Row Labels | E3: Sum of Net_Sales
A4: East | B4: 16062920 | D4: Accessories | E4: 4151277.5
A5: North | B5: 16825210 | D5: Electronics | E5: 56948930
A6: South | B6: 13353837 | D6: Grand Total | E6: 61100208
A7: West | B7: 14858241
A8: Grand Total | B8: 61100208
A13: Row Labels | B13: Sum of Net_Sales | D13: Row Labels | E13: Sum of Net_Sales
A14: Kiran | B14: 165045 | D14: January | E14: 4285684.5
A15: Grand Total | B15: 165045 | D15: February | E15: 4403843
D16: March | E16: 3705954
D17: April | E17: 5093387
D18: May | E18: 6426422.5
D19: June | E19: 5075197
D20: July | E20: 5800485.5
D21: August | E21: 4816859
D22: September | E22: 3419264.5
D23: October | E23: 6858686
D24: November | E24: 4889731.5
D25: December | E25: 6324693
D26: Grand Total | E26: 61100208

Sheet DashBoard
E1: RETAIL SALES AND LOAN ANALYSIS DASHBOARD
B4: Total Sales | D4: Total Profit | F4: Total Interest
B5: =SUM(Sales_Data!R2,Sales_Data!R2:R1001) -> 61117708 | D5: =SUM(Sales_Data!S2,Sales_Data!S2:S1001) -> 7851157.5 | F5: =SUM(Sales_Data!Z2,Sales_Data!Z2:Z1001) -> 77890076
B7: Average Emi | D7: Top Region | F7: Top Sales Person
B8: =AVERAGE(Sales_Data!AA2,Sales_Data!AA2:AA1001) -> 12127.923 | D8: North | F8: Arjun

Sheet Sales_Data
A1: Order_ID | B1: Date | C1: Region | D1: Salesperson | E1: Customer_ID | F1: Product_Code | G1: Units | H1: Unit_Price | I1: Discount_% | J1: Principal | K1: Rate | L1: Time_Years | M1: Product_Name | N1: Category | O1: Cost_Price | P1: Gross_Sales | Q1: Discount_Amount | R1: Net_Sales | S1: Profit | T1: Transaction_Id | U1: Sales_Type | V1: Performance | W1: Quarter | X1: Month | Y1: Bonus_% | Z1: Simple_Interest | AA1: Emi | AB1: Sales_Rank
A2: 1001 | B2: 19-12-2025 | C2: West | D2: Arjun | E2: C1016 | F2: P108 | G2: 7 | H2: 2500 | I2: 0 | J2: 61652 | K2: 10 | L2: 3 | M2: =VLOOKUP(Sales_Data!F2,Product_Master!$A$2:$D$11,2) -> Speaker | N2: =VLOOKUP(F2,Product_Master!$A$2:$C$11,3) -> Accessories | O2: =VLOOKUP(F2,Product_Master!$A$2:$D$11,4,FALSE) -> 1800 | P2: =H2*G2 -> 17500 | Q2: =P2*(I2/100) -> 0 | R2: =P2-Q2 -> 17500 | S2: =R2-(G2*O2) -> 4900 | T2: =_xlfn.CONCAT(Sales_Data!C2,"-",Sales_Data!E2,"-",Sales_Data!A2) -> West-C1016-1001 | U2: =IF(R2>=50000,"High Value","Regular") -> Regular | V2: {=_xlfn.IFS(R2>=100000,"Excellent",R2>=50000,"Good",R2>=20000,"Average",TRUE,"Poor")} -> Poor | W2: =ROUNDUP(MONTH(B2)/3,0) -> 4 | X2: =TEXT(B2,"mmmm") -> December | Y2: =HLOOKUP("Q"&W2,Bonus_HLookup!$A$1:$E$2,2,FALSE) -> 0.08 | Z2: =(J2*K2*L2)/100 -> 18495.6 | AA2: =PMT(K2/1200,L2*12,-J2) -> 1989.3366 | AB2: =RANK(R2,$R$2:$R$1001) -> 494
A3: 1002 | B3: 05-09-2025 | C3: North | D3: Priya | E3: C1003 | F3: P104 | G3: 8 | H3: 12000 | I3: 5 | J3: 191001 | K3: 8 | L3: 3 | M3: =VLOOKUP(Sales_Data!F3,Product_Master!$A$2:$D$11,2) -> Monitor | N3: =VLOOKUP(F3,Product_Master!$A$2:$C$11,3) -> Electronics | O3: =VLOOKUP(F3,Product_Master!$A$2:$D$11,4,FALSE) -> 9000 | P3: =H3*G3 -> 96000 | Q3: =P3*(I3/100) -> 4800 | R3: =P3-Q3 -> 91200 | S3: =R3-(G3*O3) -> 19200 | T3: =_xlfn.CONCAT(Sales_Data!C3,"-",Sales_Data!E3,"-",Sales_Data!A3) -> North-C1003-1002 | U3: =IF(R3>=50000,"High Value","Regular") -> High Value | V3: {=_xlfn.IFS(R3>=100000,"Excellent",R3>=50000,"Good",R3>=20000,"Average",TRUE,"Poor")} -> Good | W3: =ROUNDUP(MONTH(B3)/3,0) -> 3 | X3: =TEXT(B3,"mmmm") -> September | Y3: =HLOOKUP("Q"&W3,Bonus_HLookup!$A$1:$E$2,2,FALSE) -> 0.06 | Z3: =(J3*K3*L3)/100 -> 45840.24 | AA3: =PMT(K3/1200,L3*12,-J3) -> 5985.2771 | AB3: =RANK(R3,$R$2:$R$1001) -> 184
A4: 1003 | B4: 09-01-2025 | C4: North | D4: Meera | E4: C1029 | F4: P103 | G4: 2 | H4: 1500 | I4: 2 | J4: 104983 | K4: 12 | L4: 5 | M4: =VLOOKUP(Sales_Data!F4,Product_Master!$A$2:$D$11,2) -> Keyboard | N4: =VLOOKUP(F4,Product_Master!$A$2:$C$11,3) -> Accessories | O4: =VLOOKUP(F4,Product_Master!$A$2:$D$11,4,FALSE) -> 1200 | P4: =H4*G4 -> 3000 | Q4: =P4*(I4/100) -> 60 | R4: =P4-Q4 -> 2940 | S4: =R4-(G4*O4) -> 540 | T4: =_xlfn.CONCAT(Sales_Data!C4,"-",Sales_Data!E4,"-",Sales_Data!A4) -> North-C1029-1003 | U4: =IF(R4>=50000,"High Value","Regular") -> Regular | V4: {=_xlfn.IFS(R4>=100000,"Excellent",R4>=50000,"Good",R4>=20000,"Average",TRUE,"Poor")} -> Poor | W4: =ROUNDUP(MONTH(B4)/3,0) -> 1 | X4: =TEXT(B4,"mmmm") -> January | Y4: =HLOOKUP("Q"&W4,Bonus_HLookup!$A$1:$E$2,2,FALSE) -> 0.02 | Z4: =(J4*K4*L4)/100 -> 62989.8 | AA4: =PMT(K4/1200,L4*12,-J4) -> 2335.2889 | AB4: =RANK(R4,$R$2:$R$1001) -> 883
A5: 1004 | B5: 17-06-2025 | C5: North | D5: Priya | E5: C1007 | F5: P110 | G5: 8 | H5: 950 | I5: 8 | J5: 342031 | K5: 11 | L5: 1 | M5: =VLOOKUP(Sales_Data!F5,Product_Master!$A$2:$D$11,2) -> Webcam | N5: =VLOOKUP(F5,Product_Master!$A$2:$C$11,3) -> Accessories | O5: =VLOOKUP(F5,Product_Master!$A$2:$D$11,4,FALSE) -> 700 | P5: =H5*G5 -> 7600 | Q5: =P5*(I5/100) -> 608 | R5: =P5-Q5 -> 6992 | S5: =R5-(G5*O5) -> 1392 | T5: =_xlfn.CONCAT(Sales_Data!C5,"-",Sales_Data!E5,"-",Sales_Data!A5) -> North-C1007-1004 | U5: =IF(R5>=50000,"High Value","Regular") -> Regular | V5: {=_xlfn.IFS(R5>=100000,"Excellent",R5>=50000,"Good",R5>=20000,"Average",TRUE,"Poor")} -> Poor | W5: =ROUNDUP(MONTH(B5)/3,0) -> 2 | X5: =TEXT(B5,"mmmm") -> June | Y5: =HLOOKUP("Q"&W5,Bonus_HLookup!$A$1:$E$2,2,FALSE) -> 0.04 | Z5: =(J5*K5*L5)/100 -> 37623.41 | AA5: =PMT(K5/1200,L5*12,-J5) -> 30229.267 | AB5: =RANK(R5,$R$2:$R$1001) -> 722
A6: 1005 | B6: 09-05-2025 | C6: South | D6: Meera | E6: C1025 | F6: P104 | G6: 5 | H6: 12000 | I6: 8 | J6: 285916 | K6: 7 | L6: 2 | M6: =VLOOKUP(Sales_Data!F6,Product_Master!$A$2:$D$11,2) -> Monitor | N6: =VLOOKUP(F6,Product_Master!$A$2:$C$11,3) -> Electronics | O6: =VLOOKUP(F6,Product_Master!$A$2:$D$11,4,FALSE) -> 9000 | P6: =H6*G6 -> 60000 | Q6: =P6*(I6/100) -> 4800 | R6: =P6-Q6 -> 55200 | S6: =R6-(G6*O6) -> 10200 | T6: =_xlfn.CONCAT(Sales_Data!C6,"-",Sales_Data!E6,"-",Sales_Data!A6) -> South-C1025-1005 | U6: =IF(R6>=50000,"High Value","Regular") -> High Value | V6: {=_xlfn.IFS(R6>=100000,"Excellent",R6>=50000,"Good",R6>=20000,"Average",TRUE,"Poor")} -> Good | W6: =ROUNDUP(MONTH(B6)/3,0) -> 2 | X6: =TEXT(B6,"mmmm") -> May | Y6: =HLOOKUP("Q"&W6,Bonus_HLookup!$A$1:$E$2,2,FALSE) -> 0.04 | Z6: =(J6*K6*L6)/100 -> 40028.24 | AA6: =PMT(K6/1200,L6*12,-J6) -> 12801.197 | AB6: =RANK(R6,$R$2:$R$1001) -> 268
A7: 1006 | B7: 04-11-2025 | C7: West | D7: Sneha | E7: C1036 | F7: P103 | G7: 10 | H7: 1500 | I7: 2 | J7: 285509 | K7: 10 | L7: 3 | M7: =VLOOKUP(Sales_Data!F7,Product_Master!$A$2:$D$11,2) -> Keyboard | N7: =VLOOKUP(F7,Product_Master!$A$2:$C$11,3) -> Accessories | O7: =VLOOKUP(F7,Product_Master!$A$2:$D$11,4,FALSE) -> 1200 | P7: =H7*G7 -> 15000 | Q7: =P7*(I7/100) -> 300 | R7: =P7-Q7 -> 14700 | S7: =R7-(G7*O7) -> 2700 | T7: =_xlfn.CONCAT(Sales_Data!C7,"-",Sales_Data!E7,"-",Sales_Data!A7) -> West-C1036-1006 | U7: =IF(R7>=50000,"High Value","Regular") -> Regular | V7: {=_xlfn.IFS(R7>=100000,"Excellent",R7>=50000,"Good",R7>=20000,"Average",TRUE,"Poor")} -> Poor | W7: =ROUNDUP(MONTH(B7)/3,0) -> 4 | X7: =TEXT(B7,"mmmm") -> November | Y7: =HLOOKUP("Q"&W7,Bonus_HLookup!$A$1:$E$2,2,FALSE) -> 0.08 | Z7: =(J7*K7*L7)/100 -> 85652.7 | AA7: =PMT(K7/1200,L7*12,-J7) -> 9212.5723 | AB7: =RANK(R7,$R$2:$R$1001) -> 532
A8: 1007 | B8: 29-09-2025 | C8: South | D8: Priya | E8: C1036 | F8: P101 | G8: 3 | H8: 55000 | I8: 2 | J8: 251211 | K8: 8 | L8: 2 | M8: =VLOOKUP(Sales_Data!F8,Product_Master!$A$2:$D$11,2) -> Laptop | N8: =VLOOKUP(F8,Product_Master!$A$2:$C$11,3) -> Electronics | O8: =VLOOKUP(F8,Product_Master!$A$2:$D$11,4,FALSE) -> 45000 | P8: =H8*G8 -> 165000 | Q8: =P8*(I8/100) -> 3300 | R8: =P8-Q8 -> 161700 | S8: =R8-(G8*O8) -> 26700 | T8: =_xlfn.CONCAT(Sales_Data!C8,"-",Sales_Data!E8,"-",Sales_Data!A8) -> South-C1036-1007 | U8: =IF(R8>=50000,"High Value","Regular") -> High Value | V8: {=_xlfn.IFS(R8>=100000,"Excellent",R8>=50000,"Good",R8>=20000,"Average",TRUE,"Poor")} -> Excellent | W8: =ROUNDUP(MONTH(B8)/3,0) -> 3 | X8: =TEXT(B8,"mmmm") -> September | Y8: =HLOOKUP("Q"&W8,Bonus_HLookup!$A$1:$E$2,2,FALSE) -> 0.06 | Z8: =(J8*K8*L8)/100 -> 40193.76 | AA8: =PMT(K8/1200,L8*12,-J8) -> 11361.593 | AB8: =RANK(R8,$R$2:$R$1001) -> 124
A9: 1008 | B9: 20-11-2025 | C9: North | D9: Priya | E9: C1009 | F9: P109 | G9: 6 | H9: 7000 | I9: 2 | J9: 469345 | K9: 12 | L9: 3 | M9: =VLOOKUP(Sales_Data!F9,Product_Master!$A$2:$D$11,2) -> Router | N9: =VLOOKUP(F9,Product_Master!$A$2:$C$11,3) -> Electronics | O9: =VLOOKUP(F9,Product_Master!$A$2:$D$11,4,FALSE) -> 5000 | P9: =H9*G9 -> 42000 | Q9: =P9*(I9/100) -> 840 | R9: =P9-Q9 -> 41160 | S9: =R9-(G9*O9) -> 11160 | T9: =_xlfn.CONCAT(Sales_Data!C9,"-",Sales_Data!E9,"-",Sales_Data!A9) -> North-C1009-1008 | U9: =IF(R9>=50000,"High Value","Regular") -> Regular | V9: {=_xlfn.IFS(R9>=100000,"Excellent",R9>=50000,"Good",R9>=20000,"Average",TRUE,"Poor")} -> Average | W9: =ROUNDUP(MONTH(B9)/3,0) -> 4 | X9: =TEXT(B9,"mmmm") -> November | Y9: =HLOOKUP("Q"&W9,Bonus_HLookup!$A$1:$E$2,2,FALSE) -> 0.08 | Z9: =(J9*K9*L9)/100 -> 168964.2 | AA9: =PMT(K9/1200,L9*12,-J9) -> 15588.97 | AB9: =RANK(R9,$R$2:$R$1001) -> 331
A10: 1009 | B10: 12-12-2025 | C10: South | D10: Priya | E10: C1023 | F10: P106 | G10: 10 | H10: 8000 | I10: 2 | J10: 465202 | K10: 7 | L10: 5 | M10: =VLOOKUP(Sales_Data!F10,Product_Master!$A$2:$D$11,2) -> Printer | N10: =VLOOKUP(F10,Product_Master!$A$2:$C$11,3) -> Electronics | O10: =VLOOKUP(F10,Product_Master!$A$2:$D$11,4,FALSE) -> 6500 | P10: =H10*G10 -> 80000 | Q10: =P10*(I10/100) -> 1600 | R10: =P10-Q10 -> 78400 | S10: =R10-(G10*O10) -> 13400 | T10: =_xlfn.CONCAT(Sales_Data!C10,"-",Sales_Data!E10,"-",Sales_Data!A10) -> South-C1023-1009 | U10: =IF(R10>=50000,"High Value","Regular") -> High Value | V10: {=_xlfn.IFS(R10>=100000,"Excellent",R10>=50000,"Good",R10>=20000,"Average",TRUE,"Poor")} -> Good | W10: =ROUNDUP(MONTH(B10)/3,0) -> 4 | X10: =TEXT(B10,"mmmm") -> December | Y10: =HLOOKUP("Q"&W10,Bonus_HLookup!$A$1:$E$2,2,FALSE) -> 0.08 | Z10: =(J10*K10*L10)/100 -> 162820.7 | AA10: =PMT(K10/1200,L10*12,-J10) -> 9211.5572 | AB10: =RANK(R10,$R$2:$R$1001) -> 197
A11: 1010 | B11: 31-12-2025 | C11: North | D11: Priya | E11: C1028 | F11: P106 | G11: 1 | H11: 8000 | I11: 12 | J11: 294026 | K11: 12 | L11: 1 | M11: =VLOOKUP(Sales_Data!F11,Product_Master!$A$2:$D$11,2) -> Printer | N11: =VLOOKUP(F11,Product_Master!$A$2:$C$11,3) -> Electronics | O11: =VLOOKUP(F11,Product_Master!$A$2:$D$11,4,FALSE) -> 6500 | P11: =H11*G11 -> 8000 | Q11: =P11*(I11/100) -> 960 | R11: =P11-Q11 -> 7040 | S11: =R11-(G11*O11) -> 540 | T11: =_xlfn.CONCAT(Sales_Data!C11,"-",Sales_Data!E11,"-",Sales_Data!A11) -> North-C1028-1010 | U11: =IF(R11>=50000,"High Value","Regular") -> Regular | V11: {=_xlfn.IFS(R11>=100000,"Excellent",R11>=50000,"Good",R11>=20000,"Average",TRUE,"Poor")} -> Poor | W11: =ROUNDUP(MONTH(B11)/3,0) -> 4 | X11: =TEXT(B11,"mmmm") -> December | Y11: =HLOOKUP("Q"&W11,Bonus_HLookup!$A$1:$E$2,2,FALSE) -> 0.08 | Z11: =(J11*K11*L11)/100 -> 35283.12 | AA11: =PMT(K11/1200,L11*12,-J11) -> 26123.854 | AB11: =RANK(R11,$R$2:$R$1001) -> 718
A12: 1011 | B12: 20-10-2025 | C12: West | D12: Rahul | E12: C1030 | F12: P104 | G12: 4 | H12: 12000 | I12: 15 | J12: 154069 | K12: 11 | L12: 2 | M12: =VLOOKUP(Sales_Data!F12,Product_Master!$A$2:$D$11,2) -> Monitor | N12: =VLOOKUP(F12,Product_Master!$A$2:$C$11,3) -> Electronics | O12: =VLOOKUP(F12,Product_Master!$A$2:$D$11,4,FALSE) -> 9000 | P12: =H12*G12 -> 48000 | Q12: =P12*(I12/100) -> 7200 | R12: =P12-Q12 -> 40800 | S12: =R12-(G12*O12) -> 4800 | T12: =_xlfn.CONCAT(Sales_Data!C12,"-",Sales_Data!E12,"-",Sales_Data!A12) -> West-C1030-1011 | U12: =IF(R12>=50000,"High Value","Regular") -> Regular | V12: {=_xlfn.IFS(R12>=100000,"Excellent",R12>=50000,"Good",R12>=20000,"Average",TRUE,"Poor")} -> Average | W12: =ROUNDUP(MONTH(B12)/3,0) -> 4 | X12: =TEXT(B12,"mmmm") -> October | Y12: =HLOOKUP("Q"&W12,Bonus_HLookup!$A$1:$E$2,2,FALSE) -> 0.08 | Z12: =(J12*K12*L12)/100 -> 33895.18 | AA12: =PMT(K12/1200,L12*12,-J12) -> 7180.823 | AB12: =RANK(R12,$R$2:$R$1001) -> 334
A13: 1012 | B13: 17-08-2025 | C13: West | D13: Priya | E13: C1036 | F13: P110 | G13: 5 | H13: 950 | I13: 0 | J13: 306780 | K13: 8 | L13: 3 | M13: =VLOOKUP(Sales_Data!F13,Product_Master!$A$2:$D$11,2) -> Webcam | N13: =VLOOKUP(F13,Product_Master!$A$2:$C$11,3) -> Accessories | O13: =VLOOKUP(F13,Product_Master!$A$2:$D$11,4,FALSE) -> 700 | P13: =H13*G13 -> 4750 | Q13: =P13*(I13/100) -> 0 | R13: =P13-Q13 -> 4750 | S13: =R13-(G13*O13) -> 1250 | T13: =_xlfn.CONCAT(Sales_Data!C13,"-",Sales_Data!E13,"-",Sales_Data!A13) -> West-C1036-1012 | U13: =IF(R13>=50000,"High Value","Regular") -> Regular | V13: {=_xlfn.IFS(R13>=100000,"Excellent",R13>=50000,"Good",R13>=20000,"Average",TRUE,"Poor")} -> Poor | W13: =ROUNDUP(MONTH(B13)/3,0) -> 3 | X13: =TEXT(B13,"mmmm") -> August | Y13: =HLOOKUP("Q"&W13,Bonus_HLookup!$A$1:$E$2,2,FALSE) -> 0.06 | Z13: =(J13*K13*L13)/100 -> 73627.2 | AA13: =PMT(K13/1200,L13*12,-J13) -> 9613.3702 | AB13: =RANK(R13,$R$2:$R$1001) -> 797
... A1001: 2000 | B1001: 19-08-2025 | C1001: West | D1001: Anita | E1001: C1031 | F1001: P109 | G1001: 9 | H1001: 7000 | I1001: 0 | J1001: 460391 | K1001: 11 | L1001: 1 | M1001: =VLOOKUP(Sales_Data!F1001,Product_Master!$A$2:$D$11,2) -> Router | N1001: =VLOOKUP(F1001,Product_Master!$A$2:$C$11,3) -> Electronics | O1001: =VLOOKUP(F1001,Product_Master!$A$2:$D$11,4,FALSE) -> 5000 | P1001: =H1001*G1001 -> 63000 | Q1001: =P1001*(I1001/100) -> 0 | R1001: =P1001-Q1001 -> 63000 | S1001: =R1001-(G1001*O1001) -> 18000 | T1001: =_xlfn.CONCAT(Sales_Data!C1001,"-",Sales_Data!E1001,"-",Sales_Data!A1001) -> West-C1031-2000 | U1001: =IF(R1001>=50000,"High Value","Regular") -> High Value | V1001: {=_xlfn.IFS(R1001>=100000,"Excellent",R1001>=50000,"Good",R1001>=20000,"Average",TRUE,"Poor")} -> Good | W1001: =ROUNDUP(MONTH(B1001)/3,0) -> 3 | X1001: =TEXT(B1001,"mmmm") -> August | Y1001: =HLOOKUP("Q"&W1001,Bonus_HLookup!$A$1:$E$2,2,FALSE) -> 0.06 | Z1001: =(J1001*K1001*L1001)/100 -> 50643.01 | AA1001: =PMT(K1001/1200,L1001*12,-J1001) -> 40690.12 | AB1001: =RANK(R1001,$R$2:$R$1001) -> 245

Sheet Product_Master
A1: Product_Code | B1: Product_Name | C1: Category | D1: Cost_Price
A2: P101 | B2: Laptop | C2: Electronics | D2: 45000
A3: P102 | B3: Mouse | C3: Accessories | D3: 350
A4: P103 | B4: Keyboard | C4: Accessories | D4: 1200
A5: P104 | B5: Monitor | C5: Electronics | D5: 9000
A6: P105 | B6: Headset | C6: Accessories | D6: 1500
A7: P106 | B7: Printer | C7: Electronics | D7: 6500
A8: P107 | B8: Tablet | C8: Electronics | D8: 29000
A9: P108 | B9: Speaker | C9: Accessories | D9: 1800
A10: P109 | B10: Router | C10: Electronics | D10: 5000
A11: P110 | B11: Webcam | C11: Accessories | D11: 700

Sheet Bonus_HLookup
A1: Quarter | B1: Q1 | C1: Q2 | D1: Q3 | E1: Q4
A2: Bonus_% | B2: 0.02 | C2: 0.04 | D2: 0.06 | E2: 0.08
